output_format/__init__.py
output_format/rim_formatter.py
pdp12_asm/__init__.py
pdp12_asm/asm_lexer.py
pdp12_asm/asm_parse.py
pdp12_asm/model.py
pdp12_asm/parser.out
pdp12_asm/parsetab.py
pdp12_asm/pdp12_asm.py
pdp12_asm/pdp12_perm_sym.py
pdp12_asm-1.0.0b1.dist-info/LICENSE
pdp12_asm-1.0.0b1.dist-info/METADATA
pdp12_asm-1.0.0b1.dist-info/WHEEL
pdp12_asm-1.0.0b1.dist-info/entry_points.txt
pdp12_asm-1.0.0b1.dist-info/RECORD
